{
	"credit": "Made with Blockbench",
	"textures": {
		"2": "medabots_server:entity/nin_ninja/body"
	},
	"elements": [
		{
			"from": [5.7137, 25.82093, 3.8867],
			"to": [10.21476, 29.9626, 4.84198],
			"faces": {
				"north": {"uv": [0.4, 1.6, 0.1, 1.9], "texture": "#2"},
				"east": {"uv": [0.4, 1.6, 0.1, 1.9], "texture": "#2"},
				"south": {"uv": [0.4, 1.6, 0.1, 1.9], "texture": "#2"},
				"west": {"uv": [0.4, 1.6, 0.1, 1.9], "texture": "#2"},
				"up": {"uv": [0.4, 1.6, 0.1, 1.9], "texture": "#2"},
				"down": {"uv": [0.4, 1.6, 0.1, 1.9], "texture": "#2"}
			}
		},
		{
			"from": [5.70967, 24.12341, -0.13851],
			"to": [10.21072, 28.26509, 0.81678],
			"rotation": {"angle": -22.5, "axis": "x", "origin": [7.96687, 37.15709, 7.99878]},
			"faces": {
				"north": {"uv": [0.4, 1.6, 0.1, 1.9], "texture": "#2"},
				"east": {"uv": [0.4, 1.6, 0.1, 1.9], "texture": "#2"},
				"south": {"uv": [0.4, 1.6, 0.1, 1.9], "texture": "#2"},
				"west": {"uv": [0.4, 1.6, 0.1, 1.9], "texture": "#2"},
				"up": {"uv": [0.4, 1.6, 0.1, 1.9], "texture": "#2"},
				"down": {"uv": [0.4, 1.6, 0.1, 1.9], "texture": "#2"}
			}
		},
		{
			"from": [6.67135, 21.71693, 3.9209],
			"to": [9.66761, 29.9626, 15.71758],
			"rotation": {"angle": 22.5, "axis": "z", "origin": [7.9709, 38.8546, 12.05818]},
			"faces": {
				"north": {"uv": [10, 7.983, 15.983, 6], "rotation": 90, "texture": "#2"},
				"east": {"uv": [10, 7, 15.983, 12.983], "texture": "#2"},
				"south": {"uv": [4.508, 0.008, 5.492, 0.492], "texture": "#2"},
				"west": {"uv": [4.508, 0.008, 5.492, 0.492], "texture": "#2"},
				"up": {"uv": [4.508, 0.008, 5.492, 0.492], "texture": "#2"},
				"down": {"uv": [4.508, 0.008, 5.492, 0.492], "texture": "#2"}
			}
		},
		{
			"from": [6.26259, 21.71693, 3.9209],
			"to": [9.25885, 29.96255, 15.71758],
			"rotation": {"angle": -22.5, "axis": "z", "origin": [7.95923, 38.8546, 12.05818]},
			"faces": {
				"north": {"uv": [10, 6, 15.983, 7.983], "rotation": 90, "texture": "#2"},
				"east": {"uv": [5.492, 0.008, 4.508, 0.492], "texture": "#2"},
				"south": {"uv": [5.492, 0.008, 4.508, 0.492], "texture": "#2"},
				"west": {"uv": [15.983, 7, 10, 12.983], "texture": "#2"},
				"up": {"uv": [5.492, 0.008, 4.508, 0.492], "texture": "#2"},
				"down": {"uv": [5.492, 0.008, 4.508, 0.492], "texture": "#2"}
			}
		},
		{
			"from": [3.00059, 21.66858, 9.51834],
			"to": [12.87254, 29.9142, 12.39778],
			"rotation": {"angle": -22.5, "axis": "x", "origin": [9.92883, 38.85411, 10.70113]},
			"faces": {
				"north": {"uv": [5.492, 0.008, 4.508, 0.492], "texture": "#2"},
				"east": {"uv": [5.492, 0.008, 4.508, 0.492], "texture": "#2"},
				"south": {"uv": [15.983, 10, 10, 15.983], "rotation": 180, "texture": "#2"},
				"west": {"uv": [5.492, 0.008, 4.508, 0.492], "texture": "#2"},
				"up": {"uv": [5.492, 0.008, 4.508, 0.492], "rotation": 270, "texture": "#2"},
				"down": {"uv": [5.492, 0.008, 4.508, 0.492], "rotation": 90, "texture": "#2"}
			}
		},
		{
			"from": [7.08749, 27.15327, 4.1245],
			"to": [10.41584, 30.48162, 13.25084],
			"rotation": {"angle": 45, "axis": "z", "origin": [8.13236, 27.99669, 9.76487]},
			"faces": {
				"north": {"uv": [0.4, 1.6, 0.1, 1.9], "texture": "#2"},
				"east": {"uv": [0.4, 1.6, 0.1, 1.9], "texture": "#2"},
				"south": {"uv": [0.4, 1.6, 0.1, 1.9], "texture": "#2"},
				"west": {"uv": [0.4, 1.6, 0.1, 1.9], "texture": "#2"},
				"up": {"uv": [0.4, 1.6, 0.1, 1.9], "texture": "#2"},
				"down": {"uv": [0.4, 1.6, 0.1, 1.9], "texture": "#2"}
			}
		}
	],
	"display": {
		"thirdperson_righthand": {
			"scale": [0, 0, 0]
		},
		"thirdperson_lefthand": {
			"scale": [0, 0, 0]
		},
		"firstperson_righthand": {
			"translation": [0, -5.5, 0]
		},
		"firstperson_lefthand": {
			"translation": [0, -5.5, 0]
		},
		"ground": {
			"translation": [0, 2, 0],
			"scale": [0.5, 0.5, 0.5]
		},
		"gui": {
			"rotation": [30, -135, 0],
			"translation": [-0.25, -3, 0],
			"scale": [0.5, 0.5, 0.5]
		},
		"head": {
			"translation": [0, -20, 0],
			"scale": [0.7, 0.7, 0.65]
		},
		"fixed": {
			"scale": [0.6, 0.6, 0.6]
		}
	}
}